setup.cfg
setup.py
tolibaev/__init__.py
tolibaev/tolibaev.py
tolibaev.egg-info/PKG-INFO
tolibaev.egg-info/SOURCES.txt
tolibaev.egg-info/dependency_links.txt
tolibaev.egg-info/not-zip-safe
tolibaev.egg-info/top_level.txt