Metadata-Version: 2.1
Name: tolibaev
Version: 1.0
Summary: Математический модуль
Author-email: tolibaevrinat4@gmail.com
